tora/__init__.py
tora/_client.py
tora/_config.py
tora/_exceptions.py
tora/_http.py
tora/_types.py
tora/_validation.py
tora/_wrapper.py
tora-0.0.11.dist-info/METADATA
tora-0.0.11.dist-info/WHEEL
tora-0.0.11.dist-info/licenses/LICENSE
tora-0.0.11.dist-info/RECORD
